lanmanagement/__init__.py
lanmanagement/ddns.ini
lanmanagement/ddns_service_adapters.py
lanmanagement/ddns_updater.py
lanmanagement/dns_service.py
lanmanagement/utils.py
ddns_updater_ext-1.0.7.dist-info/METADATA
ddns_updater_ext-1.0.7.dist-info/WHEEL
ddns_updater_ext-1.0.7.dist-info/entry_points.txt
ddns_updater_ext-1.0.7.dist-info/top_level.txt
ddns_updater_ext-1.0.7.dist-info/RECORD
