Metadata-Version: 2.4
Name: ddns-updater-ext
Version: 1.0.7
Summary: Update DDNS services; extensible
Author-email: Andreas Paepcke <paepcke@cs.stanford.edu>
Maintainer-email: Andreas Paepcke <paepcke@cs.stanford.edu>
License-Expression: MIT
Project-URL: Homepage, https://github.com/paepcke/ddns-updater.git
Project-URL: Documentation, https://github.com/paepcke/ddns-updater
Project-URL: Repository, https://github.com/paepcke/ddns-updater
Requires-Python: >=3.10
Requires-Dist: requests>=2.32.5
Requires-Dist: dnspython>=2.8.0
Provides-Extra: test
Requires-Dist: pytest; extra == "test"
